{
  "$schema": "https://schemas.cerberauth.com/content/draft/2024-09/features.schema.json",
  "name": "SuperTokens",
  "abstract": "Open-source embedded authentication with no redirects — auth runs on your domain. Recipe-based modular architecture, self-hostable on any infrastructure, with optional managed cloud.",
  "identifier": "supertokens",
  "icon": {
    "contentUrl": "https://nacho.cerberauth.com/logos/supertokens.svg"
  },
  "website": "https://supertokens.com",
  "license": "Apache 2.0",
  "pricing": {
    "hasFreeTier": true,
    "freeTierLimit": "Unlimited (self-hosted)",
    "pricingModel": "mau",
    "pricingUrl": "https://supertokens.com/pricing",
    "plans": [
      { "name": "Self-hosted", "price": "Free" },
      { "name": "Managed Cloud", "price": "$0.02/MAU" },
      { "name": "Enterprise", "price": "Custom" }
    ]
  },
  "featureList": [
    { "identifier": "username_and_password_authentication", "status": "supported", "links": ["https://supertokens.com/docs/emailpassword/introduction"] },
    { "identifier": "social_sign_in_authentication", "status": "supported", "description": "Google, GitHub, Facebook, Apple plus custom OIDC/OAuth providers", "links": ["https://supertokens.com/docs/thirdparty/introduction"] },
    { "identifier": "magic_link_authentication", "status": "supported", "links": ["https://supertokens.com/docs/passwordless/introduction"] },
    { "identifier": "phone_passwordless_authentication", "status": "supported", "links": ["https://supertokens.com/docs/passwordless/introduction"] },
    { "identifier": "email_passwordless_authentication", "status": "supported", "links": ["https://supertokens.com/docs/passwordless/introduction"] },
    { "identifier": "passkey_authentication", "status": "supported", "links": ["https://supertokens.com/docs/webauthn/introduction"] },
    { "identifier": "anonymous_authentication", "status": "supported", "description": "Via anonymous sessions (stateless JWT tracking)", "links": ["https://supertokens.com/docs/session/introduction"] },
    { "identifier": "totp_mfa", "status": "supported", "links": ["https://supertokens.com/docs/mfa/introduction"] },
    { "identifier": "phone_code_mfa", "status": "supported", "links": ["https://supertokens.com/docs/mfa/introduction"] },
    { "identifier": "email_code_mfa", "status": "supported", "links": ["https://supertokens.com/docs/mfa/introduction"] },
    { "identifier": "push_notification_mfa", "status": "not_supported" },
    { "identifier": "adaptive_mfa", "status": "not_supported" },
    { "identifier": "saml2_protocol", "status": "supported", "links": ["https://supertokens.com/docs/saml/introduction"] },
    { "identifier": "oidc_protocol", "status": "supported", "links": ["https://supertokens.com/docs/thirdparty/introduction"] },
    { "identifier": "machine_to_machine", "status": "supported", "description": "Available on Enterprise plan", "links": ["https://supertokens.com/docs/m2m/introduction"] },
    { "identifier": "user_search", "status": "supported", "links": ["https://supertokens.com/docs/userroles/introduction"] },
    { "identifier": "bulk_user_import", "status": "supported", "links": ["https://supertokens.com/docs/userroles/introduction"] },
    { "identifier": "user_metadata", "status": "supported", "links": ["https://supertokens.com/docs/usermetadata/introduction"] },
    { "identifier": "progressive_profiling", "status": "not_supported" },
    { "identifier": "account_linking", "status": "supported", "links": ["https://supertokens.com/docs/accountlinking/introduction"] },
    { "identifier": "rbac", "status": "supported", "links": ["https://supertokens.com/docs/userroles/introduction"] },
    { "identifier": "abac", "status": "not_supported" },
    { "identifier": "fine_grained_authorization", "status": "not_supported" },
    { "identifier": "api_authorization", "status": "supported", "links": ["https://supertokens.com/docs/session/introduction"] },
    { "identifier": "brute_force_protection", "status": "supported", "links": ["https://supertokens.com/docs/session/introduction"] },
    { "identifier": "breached_password_detection", "status": "not_supported" },
    { "identifier": "bot_detection", "status": "not_supported" },
    { "identifier": "suspicious_ip_throttling", "status": "not_supported" },
    { "identifier": "device_fingerprinting", "status": "not_supported" },
    { "identifier": "organizations_multitenancy", "status": "supported", "links": ["https://supertokens.com/docs/multitenancy/introduction"] },
    { "identifier": "per_org_branding", "status": "not_supported" },
    { "identifier": "per_org_mfa_policy", "status": "not_supported" },
    { "identifier": "inbound_scim_provisioning", "status": "not_supported" },
    { "identifier": "universal_login_customization", "status": "not_supported", "description": "Embedded-only architecture — no hosted login page" },
    { "identifier": "embedded_login", "status": "supported", "description": "Core differentiator — auth on your domain, no redirects", "links": ["https://supertokens.com/docs/guides"] },
    { "identifier": "custom_domain", "status": "supported", "description": "Auth runs on your domain by default", "links": ["https://supertokens.com/docs/guides"] },
    { "identifier": "white_label", "status": "supported", "links": ["https://supertokens.com/docs/guides"] },
    { "identifier": "localization", "status": "partial" },
    { "identifier": "prebuilt_ui_components", "status": "supported", "description": "Pre-built React and React Native UI components", "links": ["https://supertokens.com/docs/guides"] },
    { "identifier": "custom_database_connections", "status": "supported", "description": "PostgreSQL or MySQL", "links": ["https://supertokens.com/docs/quickstart/supertokens-core"] },
    { "identifier": "oidc_federation", "status": "supported", "description": "Available on Enterprise plan.", "links": ["https://supertokens.com/docs/additional-verification/sso/overview"] },
    { "identifier": "saml_federation", "status": "supported", "description": "Available on Enterprise plan.", "links": ["https://supertokens.com/docs/additional-verification/sso/overview"] },
    { "identifier": "active_directory_ldap", "status": "not_supported" },
    { "identifier": "native_webhooks", "status": "supported", "links": ["https://supertokens.com/docs/session/introduction"] },
    { "identifier": "actions_extensibility", "status": "supported", "description": "Override functions in backend SDK", "links": ["https://supertokens.com/docs/guides"] },
    { "identifier": "terraform_provider", "status": "not_supported" },
    { "identifier": "lazy_migration", "status": "supported", "description": "Lazy migration plus bulk import supported", "links": ["https://supertokens.com/docs/guides"] },
    { "identifier": "password_hash_import", "status": "supported", "description": "Supports bcrypt, Argon2, and Firebase scrypt hashes", "links": ["https://supertokens.com/docs/guides"] },
    { "identifier": "login_analytics", "status": "partial" },
    { "identifier": "audit_log_retention", "status": "partial" },
    { "identifier": "audit_log_streaming", "status": "not_supported" },
    { "identifier": "consent_management", "status": "not_supported" },
    { "identifier": "region_deployment", "status": "supported", "description": "Self-hosted gives full control over data residency", "links": ["https://supertokens.com/docs/quickstart/supertokens-core"] },
    { "identifier": "private_cloud_deployment", "status": "supported", "description": "Self-hosted on any cloud provider.", "values": ["AWS", "Azure", "GCP"], "links": ["https://supertokens.com/docs/quickstart/supertokens-core"] },
    { "identifier": "nocode_flow_builder", "status": "not_supported" },
    { "identifier": "identity_proofing", "status": "not_supported" },
    { "identifier": "decentralized_identity", "status": "not_supported" },
    { "identifier": "billing_integration", "status": "not_supported" },
    { "identifier": "agentic_identity", "status": "not_supported" },
    { "identifier": "hotp_mfa", "status": "not_supported" },
    { "identifier": "u2f_mfa", "status": "not_supported" },
    { "identifier": "ws_federation_protocol", "status": "not_supported" },
    { "identifier": "azure_ad_integration", "status": "supported", "description": "Via ThirdParty recipe", "links": ["https://supertokens.com/docs/thirdparty/introduction"] },
    { "identifier": "bulk_user_export", "status": "not_supported" },
    { "identifier": "bulk_user_update_delete", "status": "supported", "links": ["https://supertokens.com/docs/userroles/introduction"] },
    { "identifier": "upsert_on_import", "status": "not_supported" },
    { "identifier": "legacy_username_import", "status": "not_supported" },
    { "identifier": "mfa_enrollment_import", "status": "not_supported" },
    { "identifier": "outbound_scim_provisioning", "status": "not_supported" },
    { "identifier": "scim_groups", "status": "not_supported" },
    { "identifier": "jit_provisioning", "status": "supported", "links": ["https://supertokens.com/docs/thirdparty/introduction"] },
    { "identifier": "app_metadata", "status": "supported", "links": ["https://supertokens.com/docs/usermetadata/introduction"] },
    { "identifier": "metadata_size_limits", "status": "not_supported" },
    { "identifier": "password_strength_policy", "status": "supported", "links": ["https://supertokens.com/docs/emailpassword/introduction"] },
    { "identifier": "username_restrictions", "status": "supported", "links": ["https://supertokens.com/docs/emailpassword/introduction"] },
    { "identifier": "abac", "status": "not_supported" },
    { "identifier": "fine_grained_authorization", "status": "not_supported" },
    { "identifier": "soc2_type2", "status": "supported", "links": ["https://supertokens.com/docs/introduction"] },
    { "identifier": "iso_27001", "status": "not_supported" },
    { "identifier": "hipaa_baa", "status": "not_supported" },
    { "identifier": "pci_dss", "status": "not_supported" },
    { "identifier": "csa_star", "status": "not_supported" },
    { "identifier": "fedramp", "status": "not_supported" },
    { "identifier": "gdpr_data_export", "status": "supported", "links": ["https://supertokens.com/docs/introduction"] },
    { "identifier": "gdpr_right_to_erasure", "status": "supported", "links": ["https://supertokens.com/docs/introduction"] },
    { "identifier": "consent_management", "status": "not_supported" },
    { "identifier": "security_center", "status": "not_supported" },
    { "identifier": "encryption_at_rest", "status": "supported", "links": ["https://supertokens.com/docs/quickstart/supertokens-core"] },
    { "identifier": "encryption_in_transit", "status": "supported", "links": ["https://supertokens.com/docs/quickstart/supertokens-core"] },
    { "identifier": "customer_managed_keys", "status": "not_supported" },
    { "identifier": "credential_guard", "status": "not_supported" },
    { "identifier": "tenant_acl", "status": "not_supported" },
    { "identifier": "device_fingerprinting", "status": "not_supported" },
    { "identifier": "per_org_branding", "status": "not_supported" },
    { "identifier": "per_org_mfa_policy", "status": "not_supported" },
    { "identifier": "inbound_scim_provisioning", "status": "not_supported" },
    { "identifier": "universal_login_customization", "status": "not_supported" },
    { "identifier": "authentication_api_rate_limits", "status": "supported", "links": ["https://supertokens.com/docs/session/introduction"] },
    { "identifier": "typescript_in_actions", "status": "supported", "links": ["https://supertokens.com/docs/guides"] },
    { "identifier": "custom_email_provider", "status": "supported", "links": ["https://supertokens.com/docs/emailpassword/introduction"] },
    { "identifier": "email_templates", "status": "supported", "links": ["https://supertokens.com/docs/emailpassword/introduction"] },
    { "identifier": "custom_oidc_claims", "status": "supported", "links": ["https://supertokens.com/docs/session/introduction"] }
  ]
}
